bin/throne.py
src/api.py
src/bgp.py
src/exceptions.py
src/ip.py
src/peeringdb.py
src/shodan.py
src/whois.py
src/parsers/json_request.py
src/parsers/lg_parser.py
src/parsers/shodan_parser.py
throne-0.6.1.dist-info/LICENSE
throne-0.6.1.dist-info/METADATA
throne-0.6.1.dist-info/WHEEL
throne-0.6.1.dist-info/entry_points.txt
throne-0.6.1.dist-info/top_level.txt
throne-0.6.1.dist-info/RECORD
