Metadata-Version: 2.1
Name: throne
Version: 0.6.1
Summary: Watch the internet from up on your throne.
Home-page: https://github.com/throne/throne-cli/
Author: throne:shrunbr
Author-email: shrunbr@throne.dev
License: BSD 3-Clause Clear License
License-File: LICENSE
Requires-Dist: Click
Requires-Dist: colorama
Requires-Dist: requests
Requires-Dist: pyyaml
